Metadata-Version: 2.1
Name: boy-gay
Version: 0.0
Summary: masage distributions
Author-email: valedol64@gmail.com
